{
  "timestamp": "2025-10-06T01:22:45.447Z",
  "purged_count": 0,
  "errors": 0,
  "next_purge": "2025-10-13T01:22:45.447Z",
  "purge_history": [
    {
      "timestamp": "2026-04-25T12:48:51.187Z",
      "purge_days": 90,
      "results": {
        "total_active": 1644,
        "total_pending": 0,
        "purged_active": 0,
        "purged_pending": 0,
        "moved_to_archived": 0
      }
    },
    {
      "timestamp": "2026-04-25T07:11:14.643Z",
      "purge_days": 90,
      "results": {
        "total_active": 1644,
        "total_pending": 0,
        "purged_active": 0,
        "purged_pending": 0,
        "moved_to_archived": 0
      }
    },
    {
      "timestamp": "2026-04-25T01:51:04.414Z",
      "purge_days": 90,
      "results": {
        "total_active": 1649,
        "total_pending": 0,
        "purged_active": 5,
        "purged_pending": 0,
        "moved_to_archived": 5
      }
    },
    {
      "timestamp": "2026-04-24T18:44:28.780Z",
      "purge_days": 90,
      "results": {
        "total_active": 1648,
        "total_pending": 0,
        "purged_active": 0,
        "purged_pending": 0,
        "moved_to_archived": 0
      }
    },
    {
      "timestamp": "2026-04-24T13:09:44.855Z",
      "purge_days": 90,
      "results": {
        "total_active": 1641,
        "total_pending": 0,
        "purged_active": 0,
        "purged_pending": 0,
        "moved_to_archived": 0
      }
    },
    {
      "timestamp": "2026-04-24T07:55:50.253Z",
      "purge_days": 90,
      "results": {
        "total_active": 1641,
        "total_pending": 0,
        "purged_active": 0,
        "purged_pending": 0,
        "moved_to_archived": 0
      }
    },
    {
      "timestamp": "2026-04-24T02:00:04.232Z",
      "purge_days": 90,
      "results": {
        "total_active": 1647,
        "total_pending": 0,
        "purged_active": 7,
        "purged_pending": 0,
        "moved_to_archived": 7
      }
    },
    {
      "timestamp": "2026-04-23T19:03:03.435Z",
      "purge_days": 90,
      "results": {
        "total_active": 1647,
        "total_pending": 0,
        "purged_active": 10,
        "purged_pending": 0,
        "moved_to_archived": 10
      }
    },
    {
      "timestamp": "2026-04-23T13:11:43.259Z",
      "purge_days": 90,
      "results": {
        "total_active": 1633,
        "total_pending": 0,
        "purged_active": 0,
        "purged_pending": 0,
        "moved_to_archived": 0
      }
    },
    {
      "timestamp": "2026-04-23T07:31:49.197Z",
      "purge_days": 90,
      "results": {
        "total_active": 1628,
        "total_pending": 0,
        "purged_active": 0,
        "purged_pending": 0,
        "moved_to_archived": 0
      }
    },
    {
      "timestamp": "2026-04-23T01:59:23.006Z",
      "purge_days": 90,
      "results": {
        "total_active": 1628,
        "total_pending": 0,
        "purged_active": 0,
        "purged_pending": 0,
        "moved_to_archived": 0
      }
    },
    {
      "timestamp": "2026-04-22T19:06:52.086Z",
      "purge_days": 90,
      "results": {
        "total_active": 1601,
        "total_pending": 0,
        "purged_active": 5,
        "purged_pending": 0,
        "moved_to_archived": 5
      }
    },
    {
      "timestamp": "2026-04-22T13:12:52.935Z",
      "purge_days": 90,
      "results": {
        "total_active": 1571,
        "total_pending": 0,
        "purged_active": 0,
        "purged_pending": 0,
        "moved_to_archived": 0
      }
    },
    {
      "timestamp": "2026-04-22T07:27:06.358Z",
      "purge_days": 90,
      "results": {
        "total_active": 1577,
        "total_pending": 0,
        "purged_active": 6,
        "purged_pending": 0,
        "moved_to_archived": 6
      }
    },
    {
      "timestamp": "2026-04-22T01:55:26.509Z",
      "purge_days": 90,
      "results": {
        "total_active": 1590,
        "total_pending": 0,
        "purged_active": 15,
        "purged_pending": 0,
        "moved_to_archived": 15
      }
    },
    {
      "timestamp": "2026-04-21T19:05:57.127Z",
      "purge_days": 90,
      "results": {
        "total_active": 1595,
        "total_pending": 0,
        "purged_active": 10,
        "purged_pending": 0,
        "moved_to_archived": 10
      }
    },
    {
      "timestamp": "2026-04-21T13:11:15.322Z",
      "purge_days": 90,
      "results": {
        "total_active": 1594,
        "total_pending": 0,
        "purged_active": 5,
        "purged_pending": 0,
        "moved_to_archived": 5
      }
    },
    {
      "timestamp": "2026-04-21T07:29:31.011Z",
      "purge_days": 90,
      "results": {
        "total_active": 1609,
        "total_pending": 0,
        "purged_active": 15,
        "purged_pending": 0,
        "moved_to_archived": 15
      }
    },
    {
      "timestamp": "2026-04-21T01:56:26.605Z",
      "purge_days": 90,
      "results": {
        "total_active": 1644,
        "total_pending": 0,
        "purged_active": 35,
        "purged_pending": 0,
        "moved_to_archived": 35
      }
    },
    {
      "timestamp": "2026-04-20T18:59:43.714Z",
      "purge_days": 90,
      "results": {
        "total_active": 1659,
        "total_pending": 0,
        "purged_active": 15,
        "purged_pending": 0,
        "moved_to_archived": 15
      }
    },
    {
      "timestamp": "2026-04-20T13:15:47.409Z",
      "purge_days": 90,
      "results": {
        "total_active": 1638,
        "total_pending": 0,
        "purged_active": 0,
        "purged_pending": 0,
        "moved_to_archived": 0
      }
    },
    {
      "timestamp": "2026-04-20T07:59:04.281Z",
      "purge_days": 90,
      "results": {
        "total_active": 1678,
        "total_pending": 0,
        "purged_active": 45,
        "purged_pending": 0,
        "moved_to_archived": 45
      }
    },
    {
      "timestamp": "2026-04-20T02:01:29.564Z",
      "purge_days": 90,
      "results": {
        "total_active": 1687,
        "total_pending": 0,
        "purged_active": 10,
        "purged_pending": 0,
        "moved_to_archived": 10
      }
    },
    {
      "timestamp": "2026-04-19T18:42:09.024Z",
      "purge_days": 90,
      "results": {
        "total_active": 1684,
        "total_pending": 0,
        "purged_active": 2,
        "purged_pending": 0,
        "moved_to_archived": 2
      }
    },
    {
      "timestamp": "2026-04-19T12:47:02.455Z",
      "purge_days": 90,
      "results": {
        "total_active": 1684,
        "total_pending": 0,
        "purged_active": 0,
        "purged_pending": 0,
        "moved_to_archived": 0
      }
    },
    {
      "timestamp": "2026-04-19T07:14:15.396Z",
      "purge_days": 90,
      "results": {
        "total_active": 1684,
        "total_pending": 0,
        "purged_active": 0,
        "purged_pending": 0,
        "moved_to_archived": 0
      }
    },
    {
      "timestamp": "2026-04-19T04:50:10.032Z",
      "purge_days": 90,
      "results": {
        "total_active": 1684,
        "total_pending": 0,
        "purged_active": 0,
        "purged_pending": 0,
        "moved_to_archived": 0
      }
    },
    {
      "timestamp": "2026-04-19T01:59:33.229Z",
      "purge_days": 90,
      "results": {
        "total_active": 1684,
        "total_pending": 0,
        "purged_active": 0,
        "purged_pending": 0,
        "moved_to_archived": 0
      }
    },
    {
      "timestamp": "2026-04-18T18:41:35.093Z",
      "purge_days": 90,
      "results": {
        "total_active": 1684,
        "total_pending": 0,
        "purged_active": 0,
        "purged_pending": 0,
        "moved_to_archived": 0
      }
    },
    {
      "timestamp": "2026-04-18T12:47:14.106Z",
      "purge_days": 90,
      "results": {
        "total_active": 1684,
        "total_pending": 0,
        "purged_active": 0,
        "purged_pending": 0,
        "moved_to_archived": 0
      }
    }
  ],
  "last_updated": "2026-04-25T12:48:51.188Z"
}
